taxotagger/__init__.py
taxotagger/abc.py
taxotagger/config.py
taxotagger/defaults.py
taxotagger/logger.py
taxotagger/models.py
taxotagger/taxotagger.py
taxotagger/utils.py
taxotagger-0.0.1a7.dist-info/LICENSE
taxotagger-0.0.1a7.dist-info/METADATA
taxotagger-0.0.1a7.dist-info/WHEEL
taxotagger-0.0.1a7.dist-info/top_level.txt
taxotagger-0.0.1a7.dist-info/RECORD
