Metadata-Version: 2.2
Name: taxotagger
Version: 0.0.1a7
Summary: Fungi DNA barcoder based on semantic searching
License: Apache-2.0 license
Project-URL: Repository, https://github.com/MycoAI/taxotagger
Keywords: Fungi,Taxonomy,Semantic search,Vector database,Machine learning
Classifier: Development Status :: 4 - Beta
Classifier: Intended Audience :: Education
Classifier: Intended Audience :: Science/Research
Classifier: License :: OSI Approved :: Apache Software License
Classifier: Natural Language :: English
Classifier: Operating System :: MacOS
Classifier: Operating System :: POSIX :: Linux
Classifier: Programming Language :: Python :: 3
Classifier: Programming Language :: Python :: 3.10
Requires-Python: >=3.10
License-File: LICENSE
Requires-Dist: httpx
Requires-Dist: mycoai-its
Requires-Dist: pydantic
Requires-Dist: pymilvus
Requires-Dist: pympler
Requires-Dist: rich
Requires-Dist: torch
Provides-Extra: dev
Requires-Dist: build; extra == "dev"
Requires-Dist: wheel; extra == "dev"
Requires-Dist: ruff; extra == "dev"
Requires-Dist: pytest; extra == "dev"
Requires-Dist: pytest-cov; extra == "dev"
Requires-Dist: pytest-order; extra == "dev"
Requires-Dist: coverage[toml]; extra == "dev"
Requires-Dist: mypy; extra == "dev"
Requires-Dist: typing_extensions; extra == "dev"
Requires-Dist: types-Deprecated; extra == "dev"
Requires-Dist: black; extra == "dev"
Requires-Dist: mkdocs; extra == "dev"
Requires-Dist: mkdocs-material; extra == "dev"
Requires-Dist: mkdocs-exclude; extra == "dev"
Requires-Dist: mkdocs-redirects; extra == "dev"
Requires-Dist: mkdocstrings-python; extra == "dev"
Requires-Dist: mike; extra == "dev"
